arb_xl/__init__.py
arb_xl/file_handler.py
arb_xl/json_to_xls.py
arb_xl/logger.py
arb_xl/main.py
arb_xl/xls_to_json.py
arb_xl-1.0.0.dist-info/LICENSE
arb_xl-1.0.0.dist-info/METADATA
arb_xl-1.0.0.dist-info/WHEEL
arb_xl-1.0.0.dist-info/entry_points.txt
arb_xl-1.0.0.dist-info/top_level.txt
arb_xl-1.0.0.dist-info/RECORD
