Metadata-Version: 2.2
Name: arb-xl
Version: 1.0.0
Summary: A CLI tool to convert JSON/ARB translation files to Excel and vice versa.
Home-page: https://github.com/abdullahalamodi/arb-xl
Author: alamodi
Author-email: alamodi326@gmail.com
Classifier: Programming Language :: Python :: 3
Classifier: License :: OSI Approved :: MIT License
Classifier: Operating System :: OS Independent
Requires-Python: >=3.7
License-File: LICENSE
Requires-Dist: pandas
Requires-Dist: openpyxl
Dynamic: author
Dynamic: author-email
Dynamic: classifier
Dynamic: description
Dynamic: description-content-type
Dynamic: home-page
Dynamic: requires-dist
Dynamic: requires-python
Dynamic: summary
